[
  {
    "article": "2016 | The Merger",
    "title": "The Merger",
    "description": "North Terrace Optometrists merges with Innovative Eye Care. The team expands.",
    "linkTitle": "",
    "linkRef": ""
  },
  {
    "article": "2012 | Fieldhouse retires",
    "title": "Fieldhouse Retirement",
    "description": "Ron Fieldhouse retires from practice.",
    "linkTitle": "",
    "linkRef": ""
  },
  {
    "article": "2010 | The Purchase",
    "title": "The Purchase",
    "description": "Lachlan Scott-Hoy purchases R Fieldhouse and Associates, now known as Innovative Eye Care.",
    "linkTitle": "",
    "linkRef": ""
  },
  {
    "article": "2007 | Lachlan - R Fieldhouse & Associates",
    "title": "Lachlan - R Fieldhouse",
    "description": "Lachlan Scott-Hoy begins working at R Fieldhouse and Associates.",
    "linkTitle": "",
    "linkRef": ""
  },
  {
    "article": "2007 | Don Noack Award",
    "title": "Don Noack Award",
    "description": "Lachlan Scott-Hoy receives the Don Noack Award for excellence in contact lenses.",
    "linkTitle": "",
    "linkRef": ""
  },
  {
    "article": "1996 | North Tce Optometrists",
    "title": "North Tce Optometrists",
    "description": "North Terrace Practice becomes known as North Terrace Optometrists.",
    "linkTitle": "",
    "linkRef": ""
  },
  {
    "article": "1984 | North Tce Practice",
    "title": "North Tce Practice",
    "description": "Kevin Rooney, Mark Parsons and Simon Leong purchase the North Terrace practice.",
    "linkTitle": "",
    "linkRef": ""
  },
  {
    "article": "1959 | R Fieldhouse & Associates",
    "title": "R Fieldhouse",
    "description": "R Fieldhouse and Associates is founded by Ron Fieldhouse.",
    "linkTitle": "",
    "linkRef": ""
  }
]
